python_vali/__init__.py
python_vali/__init__.pyi
python_vali/_python_vali.cpython-314-x86_64-linux-gnu.so
python_vali.libs/libavcodec-78ef5d7d.so.61.19.101
python_vali.libs/libavformat-3c40d271.so.61.7.100
python_vali.libs/libavutil-4118592a.so.59.39.100
python_vali.libs/libcudart-9955aa41.so.13.1.80
python_vali.libs/libswresample-30bf0a6e.so.5.3.100
python_vali.libs/libswscale-a076a69d.so.8.3.100
python_vali-4.8.7.dist-info/METADATA
python_vali-4.8.7.dist-info/WHEEL
python_vali-4.8.7.dist-info/dependency_links.txt
python_vali-4.8.7.dist-info/top_level.txt
python_vali-4.8.7.dist-info/RECORD
python_vali-4.8.7.dist-info/licenses/LICENSE
python_vali-4.8.7.dist-info/sboms/auditwheel.cdx.json
