Metadata-Version: 2.4
Name: python_vali
Version: 4.8.7
Summary: Video processing in Python
Author: Roman Arzumanyan
Author-email: Roman Arzumanyan <roman.arzum@gmail.com>
License: Apache 2.0
License-File: LICENSE
Requires-Dist: numpy
Provides-Extra: dev
Requires-Dist: torch; extra == "dev"
Requires-Dist: torchvision; extra == "dev"
Requires-Dist: onnx; extra == "dev"
Requires-Dist: tensorrt; extra == "dev"
Provides-Extra: samples
Requires-Dist: torch; extra == "samples"
Requires-Dist: torchvision; extra == "samples"
Requires-Dist: onnx; extra == "samples"
Requires-Dist: tensorrt; extra == "samples"
Requires-Dist: pynvml; extra == "samples"
Provides-Extra: tests
Requires-Dist: torch; extra == "tests"
Requires-Dist: torchvision; extra == "tests"
Requires-Dist: parameterized; extra == "tests"
Requires-Dist: pydantic; extra == "tests"
Requires-Dist: pynvml; extra == "tests"
Requires-Dist: unittest; extra == "tests"
Requires-Dist: json; extra == "tests"
Requires-Dist: logging; extra == "tests"
Requires-Dist: random; extra == "tests"
Requires-Dist: typing; extra == "tests"
Requires-Dist: math; extra == "tests"
Requires-Dist: sys; extra == "tests"
Requires-Dist: os; extra == "tests"
Provides-Extra: torch
Requires-Dist: torch; extra == "torch"
Requires-Dist: torchvision; extra == "torch"
Provides-Extra: tensorrt
Requires-Dist: torch; extra == "tensorrt"
Requires-Dist: torchvision; extra == "tensorrt"
Dynamic: author
Dynamic: description
Dynamic: description-content-type
Dynamic: license
Dynamic: license-file
Dynamic: provides-extra
Dynamic: requires-dist
